textops_api_v1/__init__.py
textops_api_v1/api.py
textops_api_v1-0.1.85.dist-info/METADATA
textops_api_v1-0.1.85.dist-info/WHEEL
textops_api_v1-0.1.85.dist-info/top_level.txt
textops_api_v1-0.1.85.dist-info/RECORD
