Metadata-Version: 2.1
Name: textops-api-v1
Version: 0.1.85
Summary: Python client for TextOps transcription API
Home-page: https://your-company-website.com
Author: Your Name
Author-email: your.email@example.com
License: UNKNOWN
Keywords: transcription,speech-to-text,api
Platform: UNKNOWN
Classifier: Development Status :: 3 - Alpha
Classifier: Intended Audience :: Developers
Classifier: Programming Language :: Python :: 3
Classifier: Programming Language :: Python :: 3.7
Classifier: Programming Language :: Python :: 3.8
Classifier: Programming Language :: Python :: 3.9
Requires-Python: >=3.7
Requires-Dist: requests>=2.25.0
